<?xml version="1.0" encoding="utf-8"?>
<Log>
	<Params>
		<Camera>
			<xPosition>0</xPosition>
			<yPosition>0</yPosition>
		</Camera>
		<Mouse>
			<scrollValue>0</scrollValue>
			<xLeftClick>813</xLeftClick>
			<xPosition>813</xPosition>
			<xRightClick>813</xRightClick>
			<y2dPosition>75</y2dPosition>
			<y2dRightClick>75</y2dRightClick>
			<yLeftClick>75</yLeftClick>
			<yPosition>75</yPosition>
			<yRightClick>75</yRightClick>
			<leftClick>1</leftClick>
			<leftHold>0</leftHold>
			<release>0</release>
			<rightClick>0</rightClick>
			<scrollBool>0</scrollBool>
		</Mouse>
		<Window>
			<heightZoomed>1173</heightZoomed>
			<ratio>1.44928</ratio>
			<widthZoomed>1700</widthZoomed>
			<shouldClose>1</shouldClose>
			<bottomBarHeight>0</bottomBarHeight>
			<topBarHeight>0</topBarHeight>
		</Window>
	</Params>
</Log>